[
  {
    "code": "HPR",
    "name": "17-HIDROXI PROGESTERONA",
    "suggested_price_from_lab": 18877,
    "price": "$30.203"
  },
  {
    "code": "NU5",
    "name": "5-NUCLEOTIDASA",
    "suggested_price_from_lab": 9536,
    "price": "$15.258"
  },
  {
    "code": "BHB",
    "name": "ACIDO BETA HIDROXI BUTIRICO",
    "suggested_price_from_lab": 42629,
    "price": "$68.206"
  },
  {
    "code": "ABI",
    "name": "ACIDOS BILIARES",
    "suggested_price_from_lab": 15047,
    "price": "$24.075"
  },
  {
    "code": "Ac graso",
    "name": "ACIDOS GRASOS SAT.DE CADENA LARGA",
    "suggested_price_from_lab": 275356,
    "price": "$440.570"
  },
  {
    "code": "ACYL",
    "name": "ACIL CARNITINA",
    "suggested_price_from_lab": 275356,
    "price": "$440.570"
  },
  {
    "code": "ACTH",
    "name": "ACTH CORTICOTROFINA",
    "suggested_price_from_lab": 4890,
    "price": "$7.824"
  },
  {
    "code": "AGUA-B",
    "name": "AGUA ANALISIS BATERIOLOGICO",
    "suggested_price_from_lab": 48552,
    "price": "$77.683"
  },
  {
    "code": "AGUA-F",
    "name": "AGUA ANALISIS FISICO QUIMICO",
    "suggested_price_from_lab": 125565,
    "price": "$200.904"
  },
  {
    "code": "ALC O",
    "name": "ALCOHOL EN ORINA",
    "suggested_price_from_lab": 7039,
    "price": "$11.262"
  },
  {
    "code": "ALC S",
    "name": "ALCOHOL EN SUERO",
    "suggested_price_from_lab": 5085,
    "price": "$8.136"
  },
  {
    "code": "ALD",
    "name": "ALDOLASA",
    "suggested_price_from_lab": 5050,
    "price": "$8.080"
  },
  {
    "code": "ALR",
    "name": "ALDOSTERONA PLASMATICA",
    "suggested_price_from_lab": 26975,
    "price": "$43.160"
  },
  {
    "code": "ALO",
    "name": "ALDOSTERONA en orina  (RIA)",
    "suggested_price_from_lab": 26975,
    "price": "$43.160"
  },
  {
    "code": "AFP",
    "name": "ALFA FETO PROTEINA",
    "suggested_price_from_lab": 4116,
    "price": "$6.586"
  },
  {
    "code": "ALP",
    "name": "ALPRAZOLAN",
    "suggested_price_from_lab": 25706,
    "price": "$41.130"
  },
  {
    "code": "AL",
    "name": "ALUMINIO",
    "suggested_price_from_lab": 40125,
    "price": "$64.200"
  },
  {
    "code": "AMS",
    "name": "AMILASEMIA",
    "suggested_price_from_lab": 1295,
    "price": "$2.072"
  },
  {
    "code": "AMU",
    "name": "AMILASURIA",
    "suggested_price_from_lab": 1295,
    "price": "$2.072"
  },
  {
    "code": "AMIO",
    "name": "AMINOACIDOS URINARIO",
    "suggested_price_from_lab": 237178,
    "price": "$379.485"
  },
  {
    "code": "AN4",
    "name": "ANDROSTENODIONA (delta 4)",
    "suggested_price_from_lab": 5734,
    "price": "$9.174"
  },
  {
    "code": "DPG A",
    "name": "ANTIC ANTI GLIADINA DEAMINADA IgA",
    "suggested_price_from_lab": 17161,
    "price": "$27.458"
  },
  {
    "code": "AT3F",
    "name": "ANTIC ANTI TROMBINA III FUNCIONAL",
    "suggested_price_from_lab": 13561,
    "price": "$21.698"
  },
  {
    "code": "BRUCE Tt",
    "name": "ANTIC. ANTI BRUCELOSIS TOTALES",
    "suggested_price_from_lab": 18974,
    "price": "$30.358"
  },
  {
    "code": "DPG G",
    "name": "GANTIC ANTI GLIADINA DEAMINADA IgG",
    "suggested_price_from_lab": 24415,
    "price": "$39.064"
  },
  {
    "code": "CCP",
    "name": "ANTIC. ANTI PEPTIDO CITRULINADO CICLICO IgG (Anti",
    "suggested_price_from_lab": 28043,
    "price": "$44.869"
  },
  {
    "code": "AATGS",
    "name": "ANTIC. ANTI TIROGLOBULINA SENSIBLE",
    "suggested_price_from_lab": 3146,
    "price": "$5.034"
  },
  {
    "code": "AAF",
    "name": "ANTIC.ANTI ACIDO FOSFATIDICO IgG",
    "suggested_price_from_lab": 11873,
    "price": "$18.997"
  },
  {
    "code": "AAM",
    "name": "ANTIC.ANTI ACIDO FOSFATIDICO IgM",
    "suggested_price_from_lab": 11678,
    "price": "$18.685"
  },
  {
    "code": "ANCA",
    "name": "ANTIC.ANTI ANCA (ANTI-GRANULOCITOS)",
    "suggested_price_from_lab": 27394,
    "price": "$43.830"
  },
  {
    "code": "BETA2G",
    "name": "ANTIC.ANTI BETA 2 GLICOPROTEINA IgA",
    "suggested_price_from_lab": 41429,
    "price": "$66.286"
  },
  {
    "code": "CARA",
    "name": "ANTIC.ANTI CARDIOLIPINAS IgA",
    "suggested_price_from_lab": 31335,
    "price": "$50.136"
  },
  {
    "code": "CAR",
    "name": "ANTIC.ANTI CARDIOLIPINAS IgG",
    "suggested_price_from_lab": 12543,
    "price": "$20.069"
  },
  {
    "code": "CAM",
    "name": "ANTIC.ANTI CARDIOLIPINAS IgM",
    "suggested_price_from_lab": 12543,
    "price": "$20.069"
  },
  {
    "code": "CENB",
    "name": "ANTIC.ANTI CENTROMERO B",
    "suggested_price_from_lab": 2909,
    "price": "$4.654"
  },
  {
    "code": "DND",
    "name": "ANTIC.ANTI DNA - IFI-",
    "suggested_price_from_lab": 10129,
    "price": "$16.206"
  },
  {
    "code": "END",
    "name": "ANTIC.ANTI ENDOMISIO IgA",
    "suggested_price_from_lab": 17391,
    "price": "$27.826"
  },
  {
    "code": "ENG",
    "name": "ANTIC.ANTI ENDOMISIO IgG",
    "suggested_price_from_lab": 16986,
    "price": "$27.178"
  },
  {
    "code": "AAFOL G",
    "name": "ANTIC.ANTI FOSFOLIPIDOS IgG",
    "suggested_price_from_lab": 15033,
    "price": "$24.053"
  },
  {
    "code": "AAFOL M",
    "name": "ANTIC.ANTI FOSFOLIPIDOS IgM",
    "suggested_price_from_lab": 15033,
    "price": "$24.053"
  },
  {
    "code": "GAA",
    "name": "ANTIC.ANTI GLIADINA IgA",
    "suggested_price_from_lab": 9717,
    "price": "$15.547"
  },
  {
    "code": "GAG",
    "name": "ANTIC.ANTI GLIADINA IgG",
    "suggested_price_from_lab": 9717,
    "price": "$15.547"
  },
  {
    "code": "AAH",
    "name": "ANTIC.ANTI HISTONA",
    "suggested_price_from_lab": 22692,
    "price": "$36.307"
  },
  {
    "code": "AAI",
    "name": "ANTIC.ANTI INSULINA",
    "suggested_price_from_lab": 19714,
    "price": "$31.542"
  },
  {
    "code": "AJO",
    "name": "ANTIC.ANTI JO1",
    "suggested_price_from_lab": 14928,
    "price": "$23.885"
  },
  {
    "code": "MII",
    "name": "ANTIC.ANTI MITOCONDRIAL IFI",
    "suggested_price_from_lab": 8266,
    "price": "$13.226"
  },
  {
    "code": "MII M2",
    "name": "ANTIC.ANTI MITOCONDRIAL M2",
    "suggested_price_from_lab": 23732,
    "price": "$37.971"
  },
  {
    "code": "AME",
    "name": "ANTIC.ANTI MUSCULO ESTRIADO",
    "suggested_price_from_lab": 4220,
    "price": "$6.752"
  },
  {
    "code": "FAN",
    "name": "ANTIC.ANTI NUCLEARES IFI (FAN)",
    "suggested_price_from_lab": 7757,
    "price": "$12.411"
  },
  {
    "code": "AARPQ",
    "name": "ANTIC.ANTI PLAQUETAS",
    "suggested_price_from_lab": 257087,
    "price": "$411.339"
  },
  {
    "code": "AP3",
    "name": "ANTIC.ANTI PROTEINASE 3",
    "suggested_price_from_lab": 21248,
    "price": "$33.997"
  },
  {
    "code": "TRAB",
    "name": "ANTIC.ANTI RECEPTOR DE TSH (TRAB)",
    "suggested_price_from_lab": 20788,
    "price": "$33.261"
  },
  {
    "code": "RNP",
    "name": "ANTIC.ANTI RNP",
    "suggested_price_from_lab": 15298,
    "price": "$24.477"
  },
  {
    "code": "ARO",
    "name": "ANTIC.ANTI SSA (o ANTI RO)",
    "suggested_price_from_lab": 14028,
    "price": "$22.445"
  },
  {
    "code": "Ala",
    "name": "ANTIC.ANTI SSB (o ANTI La)",
    "suggested_price_from_lab": 14028,
    "price": "$22.445"
  },
  {
    "code": "SCL",
    "name": "ANTIC.ANTI Scl 70",
    "suggested_price_from_lab": 14028,
    "price": "$22.445"
  },
  {
    "code": "ASM",
    "name": "ANTIC.ANTI Sm (Smith)",
    "suggested_price_from_lab": 14028,
    "price": "$22.445"
  },
  {
    "code": "AATG",
    "name": "ANTIC.ANTI TIROGLOBULINA",
    "suggested_price_from_lab": 3146,
    "price": "$5.034"
  },
  {
    "code": "TPO",
    "name": "ANTIC.ANTI TIROPEROXIDASA",
    "suggested_price_from_lab": 2909,
    "price": "$4.654"
  },
  {
    "code": "ATG A",
    "name": "ANTIC.ANTI TRANSGLUTAMINASA IgA",
    "suggested_price_from_lab": 11705,
    "price": "$18.728"
  },
  {
    "code": "ATG G",
    "name": "ANTIC.ANTI TRANSGLUTAMINASA IgG",
    "suggested_price_from_lab": 19302,
    "price": "$30.883"
  },
  {
    "code": "ASO",
    "name": "ANTIESTREPTOLISINA \"O",
    "suggested_price_from_lab": 3286,
    "price": "$5.258"
  },
  {
    "code": "PSA",
    "name": "ANTIGENO PROSTATICO ESPECIFICO (PSA)",
    "suggested_price_from_lab": 3507,
    "price": "$5.611"
  },
  {
    "code": "PSA-L",
    "name": "ANTIGENO PROSTATICO ESPECIFICO (PSA) - Libre",
    "suggested_price_from_lab": 6195,
    "price": "$9.912"
  },
  {
    "code": "ATRMF",
    "name": "ANTITRIPSINA EN M. FECAL",
    "suggested_price_from_lab": 7276,
    "price": "$11.642"
  },
  {
    "code": "APO A",
    "name": "APOLIPOPROTEINA \"A",
    "suggested_price_from_lab": 4639,
    "price": "$7.422"
  },
  {
    "code": "APO B",
    "name": "APOLIPOPROTEINA \"B",
    "suggested_price_from_lab": 4639,
    "price": "$7.422"
  },
  {
    "code": "ARL",
    "name": "ARTRITIS REUMATOIDEA P DEL LATEX",
    "suggested_price_from_lab": 4360,
    "price": "$6.976"
  },
  {
    "code": "AAS",
    "name": "ASCORBICO ACIDO",
    "suggested_price_from_lab": 42336,
    "price": "$67.738"
  },
  {
    "code": "BARTO G",
    "name": "BARTONELLA HENSELAE IgG",
    "suggested_price_from_lab": 49438,
    "price": "$79.101"
  },
  {
    "code": "BARTO M",
    "name": "BARTONELLA HENSELAE IgM",
    "suggested_price_from_lab": 49438,
    "price": "$79.101"
  },
  {
    "code": "BEN",
    "name": "BENZODIACEPINA",
    "suggested_price_from_lab": 11587,
    "price": "$18.539"
  },
  {
    "code": "B2M",
    "name": "BETA 2 MICROGLOBULINA",
    "suggested_price_from_lab": 4660,
    "price": "$7.456"
  },
  {
    "code": "B2O",
    "name": "BETA 2 MICROGLOBULINA en orina",
    "suggested_price_from_lab": 4660,
    "price": "$7.456"
  },
  {
    "code": "BCROSS",
    "name": "BETA CROSSLAPS",
    "suggested_price_from_lab": 16679,
    "price": "$26.686"
  },
  {
    "code": "BRR",
    "name": "BILIRRUBINEMIA TOT.DIR.INDIR.",
    "suggested_price_from_lab": 580,
    "price": "$928"
  },
  {
    "code": "BPG",
    "name": "BORDETELLA PERTUSSIS IgG",
    "suggested_price_from_lab": 25497,
    "price": "$40.795"
  },
  {
    "code": "BPM",
    "name": "BORDETELLA PERTUSSIS IgM",
    "suggested_price_from_lab": 25497,
    "price": "$40.795"
  },
  {
    "code": "C125",
    "name": "CA 125 (ovario)",
    "suggested_price_from_lab": 4744,
    "price": "$7.590"
  },
  {
    "code": "C15",
    "name": "CA 15/3 (mama)",
    "suggested_price_from_lab": 4618,
    "price": "$7.389"
  },
  {
    "code": "C19",
    "name": "CA 19/9 (Digest.Ginecolog.)",
    "suggested_price_from_lab": 4179,
    "price": "$6.686"
  },
  {
    "code": "C21",
    "name": "CA 21-1",
    "suggested_price_from_lab": 28531,
    "price": "$45.650"
  },
  {
    "code": "C72",
    "name": "CA 72-4",
    "suggested_price_from_lab": 18653,
    "price": "$29.845"
  },
  {
    "code": "CLKL",
    "name": "CADENAS LIVIANAS en suero cuali",
    "suggested_price_from_lab": 68768,
    "price": "$110.029"
  },
  {
    "code": "CKL",
    "name": "CADENAS LIVIANAS,KAPPA Y LAMBDA CUANTI",
    "suggested_price_from_lab": 65677,
    "price": "$105.083"
  },
  {
    "code": "CAIL",
    "name": "CALCIO IONICO L",
    "suggested_price_from_lab": 2288,
    "price": "$3.661"
  },
  {
    "code": "CAS",
    "name": "CALCIO SERICO TOTAL",
    "suggested_price_from_lab": 1105,
    "price": "$1.768"
  },
  {
    "code": "CAU",
    "name": "CALCIO en orina",
    "suggested_price_from_lab": 1105,
    "price": "$1.768"
  },
  {
    "code": "CAUE",
    "name": "CALCIO en orina espontanea",
    "suggested_price_from_lab": 1108,
    "price": "$1.773"
  },
  {
    "code": "CAL",
    "name": "CALCITONINA Plasmática",
    "suggested_price_from_lab": 6780,
    "price": "$10.848"
  },
  {
    "code": "C BILIAR",
    "name": "CALCULO BILIAR",
    "suggested_price_from_lab": 29368,
    "price": "$46.989"
  },
  {
    "code": "CBZ",
    "name": "CARBAMAZEPINA",
    "suggested_price_from_lab": 5316,
    "price": "$8.506"
  },
  {
    "code": "BGT",
    "name": "CARIOTIPO-BANDEO G-T",
    "suggested_price_from_lab": 442846,
    "price": "$708.554"
  },
  {
    "code": "CATP",
    "name": "CATECOLAMINAS PLASMATICAS",
    "suggested_price_from_lab": 46096,
    "price": "$73.754"
  },
  {
    "code": "CD3",
    "name": "CD 3 SUBPOBLACION LINFOCITARIA POR CF",
    "suggested_price_from_lab": 27331,
    "price": "$43.730"
  },
  {
    "code": "CD57",
    "name": "CD 4 SUBPOBLAC. LINFOCITARIA Citometria de fluj",
    "suggested_price_from_lab": 27324,
    "price": "$43.718"
  },
  {
    "code": "CD4",
    "name": "CD 4 SUBPOBLACION LINFOCITARIA POR CF",
    "suggested_price_from_lab": 27324,
    "price": "$43.718"
  },
  {
    "code": "CEA",
    "name": "CEA ANTIG CARCINOEMBRIONARIO",
    "suggested_price_from_lab": 4116,
    "price": "$6.586"
  },
  {
    "code": "CHAT",
    "name": "CHAGAS ANTIC. TOTALES",
    "suggested_price_from_lab": 3355,
    "price": "$5.368"
  },
  {
    "code": "CP",
    "name": "CERULOPLASMINA",
    "suggested_price_from_lab": 12917,
    "price": "$20.667"
  },
  {
    "code": "CHI",
    "name": "CHAGAS IFI IgG",
    "suggested_price_from_lab": 4367,
    "price": "$6.987"
  },
  {
    "code": "CHM",
    "name": "CHAGAS IFI IgM",
    "suggested_price_from_lab": 6474,
    "price": "$10.358"
  },
  {
    "code": "CHH",
    "name": "CHAGAS POR HEMAGLUTINACION IND HAI",
    "suggested_price_from_lab": 10380,
    "price": "$16.608"
  },
  {
    "code": "CLNE G",
    "name": "CHLAMYDIA PNEUMONIAE  IgG",
    "suggested_price_from_lab": 13952,
    "price": "$22.323"
  },
  {
    "code": "CLNE M",
    "name": "CHLAMYDIA PNEUMONIAE  IgM",
    "suggested_price_from_lab": 13952,
    "price": "$22.323"
  },
  {
    "code": "CLTR A",
    "name": "CHLAMYDIA TRACHOMATIS  IgA",
    "suggested_price_from_lab": 55000,
    "price": "$88.000"
  },
  {
    "code": "CLTR G",
    "name": "CHLAMYDIA TRACHOMATIS  IgG",
    "suggested_price_from_lab": 13952,
    "price": "$22.323"
  },
  {
    "code": "CLTR M",
    "name": "CHLAMYDIA TRACHOMATIS  IgM",
    "suggested_price_from_lab": 13952,
    "price": "$22.323"
  },
  {
    "code": "CLTR AgH V",
    "name": "CHLAMYDIA TRACHOMATIS ANTIGENO HISOPADO SOLO VAGINAL",
    "suggested_price_from_lab": 54703,
    "price": "$87.525"
  },
  {
    "code": "CLTR AgH SU",
    "name": "CHLAMYDIA TRACHOMATIS ANTIGENO HISOPADO(SEMEN, URETRAL)",
    "suggested_price_from_lab": 95000,
    "price": "$152.000"
  },
  {
    "code": "CIS",
    "name": "CISTINURIA",
    "suggested_price_from_lab": 14447,
    "price": "$23.115"
  },
  {
    "code": "CMV G",
    "name": "CITOMEGALOVIRUS ANTIC. IgG",
    "suggested_price_from_lab": 3927,
    "price": "$6.283"
  },
  {
    "code": "CMV M",
    "name": "CITOMEGALOVIRUS ANTIC. IgM",
    "suggested_price_from_lab": 6732,
    "price": "$10.771"
  },
  {
    "code": "CIT",
    "name": "CITRICO ACIDO Orina",
    "suggested_price_from_lab": 17265,
    "price": "$27.624"
  },
  {
    "code": "CITRICO",
    "name": "CITRICO ACIDO Suero",
    "suggested_price_from_lab": 5629,
    "price": "$9.006"
  },
  {
    "code": "ACS",
    "name": "CITRICO ACIDO en plasma seminal",
    "suggested_price_from_lab": 22811,
    "price": "$36.498"
  },
  {
    "code": "CBN",
    "name": "CLOBAZAN",
    "suggested_price_from_lab": 37160,
    "price": "$59.456"
  },
  {
    "code": "CNZ",
    "name": "CLONAZEPAN",
    "suggested_price_from_lab": 29250,
    "price": "$46.800"
  },
  {
    "code": "CLOS",
    "name": "CLOSTRIDIUM DIFFICILE TOXINA A+B INVEST.DE",
    "suggested_price_from_lab": 100452,
    "price": "$160.723"
  },
  {
    "code": "CLOZAP",
    "name": "CLOZAPINA DETERMINACION DE",
    "suggested_price_from_lab": 35646,
    "price": "$57.034"
  },
  {
    "code": "COA",
    "name": "COAGULOGRAMA BASICO",
    "suggested_price_from_lab": 2979,
    "price": "$4.766"
  },
  {
    "code": "CU",
    "name": "COBRE EN SANGRE",
    "suggested_price_from_lab": 48447,
    "price": "$77.515"
  },
  {
    "code": "CU-U",
    "name": "COBRE en orina",
    "suggested_price_from_lab": 48447,
    "price": "$77.515"
  },
  {
    "code": "COCAINA",
    "name": "COCAINA en orina",
    "suggested_price_from_lab": 11594,
    "price": "$18.550"
  },
  {
    "code": "COFACTOR",
    "name": "COFACTOR DE RISTOCETINA",
    "suggested_price_from_lab": 45761,
    "price": "$73.218"
  },
  {
    "code": "HDL",
    "name": "COLESTEROL HDL",
    "suggested_price_from_lab": 1205,
    "price": "$1.928"
  },
  {
    "code": "LDL",
    "name": "COLESTEROL LDL",
    "suggested_price_from_lab": 709,
    "price": "$1.134"
  },
  {
    "code": "COL",
    "name": "COLESTEROL TOTAL",
    "suggested_price_from_lab": 1404,
    "price": "$2.246"
  },
  {
    "code": "VLD",
    "name": "COLESTEROL VLDL",
    "suggested_price_from_lab": 921,
    "price": "$1.474"
  },
  {
    "code": "COLPSE",
    "name": "COLINESTERASA / PSEUDOCOLINESTERASA",
    "suggested_price_from_lab": 1055,
    "price": "$1.688"
  },
  {
    "code": "C50",
    "name": "COMPLEMENTO Actividad total (CH50)",
    "suggested_price_from_lab": 120235,
    "price": "$192.376"
  },
  {
    "code": "C1Q",
    "name": "COMPLEMENTO C1Q",
    "suggested_price_from_lab": 51907,
    "price": "$83.051"
  },
  {
    "code": "C3",
    "name": "COMPLEMENTO INMUNOQ. C3",
    "suggested_price_from_lab": 1974,
    "price": "$3.158"
  },
  {
    "code": "C4",
    "name": "COMPLEMENTO INMUNOQ. C4",
    "suggested_price_from_lab": 1974,
    "price": "$3.158"
  },
  {
    "code": "CBI",
    "name": "COOMBS INDIRECTA",
    "suggested_price_from_lab": 43281,
    "price": "$69.250"
  },
  {
    "code": "CBD",
    "name": "COOMBS DIRECTA PRUEBA",
    "suggested_price_from_lab": 29116,
    "price": "$46.586"
  },
  {
    "code": "CMF",
    "name": "COPROCULTIVO",
    "suggested_price_from_lab": 11482,
    "price": "$18.371"
  },
  {
    "code": "CPO",
    "name": "COPROPORFIRINAS en orina",
    "suggested_price_from_lab": 18535,
    "price": "$29.656"
  },
  {
    "code": "COR",
    "name": "CORTISOL PLASMATICO",
    "suggested_price_from_lab": 2916,
    "price": "$4.666"
  },
  {
    "code": "COR-S",
    "name": "CORTISOL SALIVAL",
    "suggested_price_from_lab": 5085,
    "price": "$8.136"
  },
  {
    "code": "COR-U",
    "name": "CORTISOL URINARIO",
    "suggested_price_from_lab": 2916,
    "price": "$4.666"
  },
  {
    "code": "COR-V",
    "name": "CORTISOL VESPERTINO",
    "suggested_price_from_lab": 2916,
    "price": "$4.666"
  },
  {
    "code": "CPK",
    "name": "CREATINQUINASA CPK",
    "suggested_price_from_lab": 2090,
    "price": "$3.344"
  },
  {
    "code": "CKM",
    "name": "CPK-MB",
    "suggested_price_from_lab": 5636,
    "price": "$9.018"
  },
  {
    "code": "CDC",
    "name": "CREATININA CLEARENCE O DEPURAC.",
    "suggested_price_from_lab": 2891,
    "price": "$4.626"
  },
  {
    "code": "AS-CR-U",
    "name": "CREATININA en orina",
    "suggested_price_from_lab": 1445,
    "price": "$2.312"
  },
  {
    "code": "CRE",
    "name": "CREATININA en sangre",
    "suggested_price_from_lab": 1445,
    "price": "$2.312"
  },
  {
    "code": "CRG",
    "name": "CRIOGLOBULINAS",
    "suggested_price_from_lab": 4513,
    "price": "$7.221"
  },
  {
    "code": "CALCSAL",
    "name": "Calculo Salival",
    "suggested_price_from_lab": 29368,
    "price": "$46.989"
  },
  {
    "code": "CRUE",
    "name": "Creatinina en orina espontanea",
    "suggested_price_from_lab": 1445,
    "price": "$2.312"
  },
  {
    "code": "DHEAS",
    "name": "DEHIDROEPIANDROSTERONA",
    "suggested_price_from_lab": 34168,
    "price": "$54.669"
  },
  {
    "code": "DENGUE",
    "name": "DENGUE NS1 + Anticuerpos IgM+IgG",
    "suggested_price_from_lab": 86500,
    "price": "$138.400"
  },
  {
    "code": "DMD",
    "name": "DIMERO \"D",
    "suggested_price_from_lab": 29326,
    "price": "$46.922"
  },
  {
    "code": "DOP",
    "name": "DOPAMINA PLASMATICA",
    "suggested_price_from_lab": 27764,
    "price": "$44.422"
  },
  {
    "code": "DOO",
    "name": "DOPAMINA TOTAL O LIBRE orina",
    "suggested_price_from_lab": 27429,
    "price": "$43.886"
  },
  {
    "code": "ANG",
    "name": "ENZIMA CONVERTIDORA DE ANGIOTENSINA (ECA)",
    "suggested_price_from_lab": 38144,
    "price": "$61.030"
  },
  {
    "code": "EB VCA G",
    "name": "EPSTEIN BARR Ac. VCA IgG CAPSIDE",
    "suggested_price_from_lab": 5769,
    "price": "$9.230"
  },
  {
    "code": "EB VCA M",
    "name": "EPSTEIN BARR Ac. VCA IgM CAPSIDE",
    "suggested_price_from_lab": 6481,
    "price": "$10.370"
  },
  {
    "code": "EBNA G",
    "name": "EPSTEIN BARR EARLY ANTIGEN Ac.IgG",
    "suggested_price_from_lab": 27387,
    "price": "$43.819"
  },
  {
    "code": "EPY",
    "name": "ERITROPOYETINA",
    "suggested_price_from_lab": 10966,
    "price": "$17.546"
  },
  {
    "code": "ERI",
    "name": "ERITROSEDIMENTACION",
    "suggested_price_from_lab": 580,
    "price": "$928"
  },
  {
    "code": "ESPC",
    "name": "ESPERMOCULTIVO",
    "suggested_price_from_lab": 20090,
    "price": "$32.144"
  },
  {
    "code": "ESP",
    "name": "ESPERMOGRAMA",
    "suggested_price_from_lab": 7020,
    "price": "$11.232"
  },
  {
    "code": "E2",
    "name": "ESTRADIOL PLASMASTICO",
    "suggested_price_from_lab": 2402,
    "price": "$3.843"
  },
  {
    "code": "DOMI",
    "name": "EXTRACCION a DOMICILIO",
    "suggested_price_from_lab": 8545,
    "price": "$13.672"
  },
  {
    "code": "ANAL-EX",
    "name": "EXUDADO ANAL",
    "suggested_price_from_lab": 11489,
    "price": "$18.382"
  },
  {
    "code": "ENF",
    "name": "EXUDADO DE FAUCES",
    "suggested_price_from_lab": 11489,
    "price": "$18.382"
  },
  {
    "code": "FR",
    "name": "FACTOR REUMATOIDEO (FR)",
    "suggested_price_from_lab": 2434,
    "price": "$3.894"
  },
  {
    "code": "FC2",
    "name": "FACTOR II de coagulacion",
    "suggested_price_from_lab": 6104,
    "price": "$9.766"
  },
  {
    "code": "FC9",
    "name": "FACTOR IX de coagulacion",
    "suggested_price_from_lab": 10171,
    "price": "$16.274"
  },
  {
    "code": "FC5",
    "name": "FACTOR V de coagulacion",
    "suggested_price_from_lab": 10171,
    "price": "$16.274"
  },
  {
    "code": "FC7",
    "name": "FACTOR VII de coagulacion",
    "suggested_price_from_lab": 10408,
    "price": "$16.653"
  },
  {
    "code": "FC8",
    "name": "FACTOR VIII de coagulacion",
    "suggested_price_from_lab": 10171,
    "price": "$16.274"
  },
  {
    "code": "FC10",
    "name": "FACTOR X de coagulacion",
    "suggested_price_from_lab": 10408,
    "price": "$16.653"
  },
  {
    "code": "AFA",
    "name": "FENIL ACETICO ACIDO",
    "suggested_price_from_lab": 28147,
    "price": "$45.035"
  },
  {
    "code": "FEB",
    "name": "FENOBARBITAL",
    "suggested_price_from_lab": 5044,
    "price": "$8.070"
  },
  {
    "code": "FER",
    "name": "FERREMIA",
    "suggested_price_from_lab": 1373,
    "price": "$2.197"
  },
  {
    "code": "FET",
    "name": "FERRITINA",
    "suggested_price_from_lab": 2979,
    "price": "$4.766"
  },
  {
    "code": "FIB",
    "name": "FIBRINOGENO EN SANGRE",
    "suggested_price_from_lab": 1667,
    "price": "$2.667"
  },
  {
    "code": "AFO",
    "name": "FOLICO ACIDO",
    "suggested_price_from_lab": 4632,
    "price": "$7.411"
  },
  {
    "code": "AFO ERI",
    "name": "FOLICO ACIDO ERITROCITARIO",
    "suggested_price_from_lab": 5462,
    "price": "$8.739"
  },
  {
    "code": "AC FORM",
    "name": "FORMICO ACIDO en ORINA",
    "suggested_price_from_lab": 17628,
    "price": "$28.205"
  },
  {
    "code": "FAP",
    "name": "FOSFATASA ACIDA PROSTATICA",
    "suggested_price_from_lab": 1194,
    "price": "$1.910"
  },
  {
    "code": "FAL",
    "name": "FOSFATASA ALCALINA (FAL)",
    "suggested_price_from_lab": 2204,
    "price": "$3.526"
  },
  {
    "code": "FAL-O",
    "name": "FOSFATASA ALCALINA Osea (FAL O)",
    "suggested_price_from_lab": 15193,
    "price": "$24.309"
  },
  {
    "code": "FOU",
    "name": "FOSFATURIA",
    "suggested_price_from_lab": 614,
    "price": "$982"
  },
  {
    "code": "FOS",
    "name": "FOSFORO en sangre",
    "suggested_price_from_lab": 614,
    "price": "$982"
  },
  {
    "code": "ALG",
    "name": "FRUCTOSAMINA",
    "suggested_price_from_lab": 1123,
    "price": "$1.797"
  },
  {
    "code": "FSH",
    "name": "FSH",
    "suggested_price_from_lab": 1967,
    "price": "$3.147"
  },
  {
    "code": "FTA",
    "name": "FTA-ABS por IFI (ac. totales)",
    "suggested_price_from_lab": 3844,
    "price": "$6.150"
  },
  {
    "code": "GAs",
    "name": "GASTRINA",
    "suggested_price_from_lab": 5943,
    "price": "$9.509"
  },
  {
    "code": "GS",
    "name": "GLAE/SBGH",
    "suggested_price_from_lab": 9479,
    "price": "$15.166"
  },
  {
    "code": "GLU",
    "name": "GLUCEMIA",
    "suggested_price_from_lab": 938,
    "price": "$1.501"
  },
  {
    "code": "GPP",
    "name": "GLUCEMIA POST PRANDIAL",
    "suggested_price_from_lab": 2199,
    "price": "$3.518"
  },
  {
    "code": "GGT",
    "name": "GLUTAMIL TRANSPEPTIDASA GAMMA",
    "suggested_price_from_lab": 1095,
    "price": "$1.752"
  },
  {
    "code": "GOC V",
    "name": "GONORREA CULTIVO SOLO VAGINAL",
    "suggested_price_from_lab": 54703,
    "price": "$87.525"
  },
  {
    "code": "GOC SU",
    "name": "GONORREA CULTIVO (SEMEN, URETRAL)",
    "suggested_price_from_lab": 95000,
    "price": "$152.000"
  },
  {
    "code": "GRU",
    "name": "GRUPO SANGUINEO",
    "suggested_price_from_lab": 5023,
    "price": "$8.037"
  },
  {
    "code": "HPY G",
    "name": "HELICOBACTER PYLORI Elisa IgG",
    "suggested_price_from_lab": 15723,
    "price": "$25.157"
  },
  {
    "code": "HPY M",
    "name": "HELICOBACTER PYLORI Elisa IgM",
    "suggested_price_from_lab": 29278,
    "price": "$46.845"
  },
  {
    "code": "HDH",
    "name": "HEMOGLOBINA ELECTROFORESIS DE",
    "suggested_price_from_lab": 14426,
    "price": "$23.082"
  },
  {
    "code": "HGY",
    "name": "HEMOGLOBINA GLICOSILADA",
    "suggested_price_from_lab": 3195,
    "price": "$5.112"
  },
  {
    "code": "HEM",
    "name": "HEMOGRAMA",
    "suggested_price_from_lab": 2426,
    "price": "$3.882"
  },
  {
    "code": "HAV ac G",
    "name": "HEPAT. A  ANTIC.ANTI IgG",
    "suggested_price_from_lab": 5057,
    "price": "$8.091"
  },
  {
    "code": "HAV ac M",
    "name": "HEPAT. A  ANTIC.ANTI IgM",
    "suggested_price_from_lab": 5127,
    "price": "$8.203"
  },
  {
    "code": "HBSAG",
    "name": "HEPAT. B ANTIG. DE SUP (HBsAg)",
    "suggested_price_from_lab": 2602,
    "price": "$4.163"
  },
  {
    "code": "HBC Ac G",
    "name": "HEPAT. B Ag. CORE, Ac. IgG",
    "suggested_price_from_lab": 3069,
    "price": "$4.910"
  },
  {
    "code": "HBC Ac M",
    "name": "HEPAT. B Ag. CORE, Ac. IgM",
    "suggested_price_from_lab": 6271,
    "price": "$10.034"
  },
  {
    "code": "HBS Ac",
    "name": "HEPAT. B Ag. DE SUP  ANTIC.ANTI",
    "suggested_price_from_lab": 3132,
    "price": "$5.011"
  },
  {
    "code": "HB-CV",
    "name": "HEPAT. B CARGA VIRAL",
    "suggested_price_from_lab": 184266,
    "price": "$294.826"
  },
  {
    "code": "HCV G",
    "name": "HEPAT. C ANTIC.ANTI IgG ELISA",
    "suggested_price_from_lab": 4758,
    "price": "$7.613"
  },
  {
    "code": "HBcAc-T",
    "name": "HEPATITIS B - ANTIC ANTI CORE TOTAL",
    "suggested_price_from_lab": 3069,
    "price": "$4.910"
  },
  {
    "code": "HBCORE",
    "name": "HEPATITIS B CORE IGG",
    "suggested_price_from_lab": 3069,
    "price": "$4.910"
  },
  {
    "code": "HEP",
    "name": "HEPATOGRAMA",
    "suggested_price_from_lab": 3873,
    "price": "$6.197"
  },
  {
    "code": "HV1 GE",
    "name": "HERPES I ANTIC ANTI IGG ELISA",
    "suggested_price_from_lab": 8838,
    "price": "$14.141"
  },
  {
    "code": "VHSM",
    "name": "HERPES I ANTIC. ANTI IgM",
    "suggested_price_from_lab": 10792,
    "price": "$17.267"
  },
  {
    "code": "VHSG",
    "name": "HERPES II ANTIC. ANTI IgG",
    "suggested_price_from_lab": 8838,
    "price": "$14.141"
  },
  {
    "code": "VHSM2",
    "name": "HERPES II ANTIC. ANTI IgM",
    "suggested_price_from_lab": 10785,
    "price": "$17.256"
  },
  {
    "code": "AC HIP",
    "name": "HIPURICO ACIDO",
    "suggested_price_from_lab": 17809,
    "price": "$28.494"
  },
  {
    "code": "HIV CV",
    "name": "HIV CARGA VIRAL",
    "suggested_price_from_lab": 96469,
    "price": "$154.350"
  },
  {
    "code": "HIV",
    "name": "HIV - Anticuerpos anti HIV + Antigeno P24",
    "suggested_price_from_lab": 3692,
    "price": "$5.907"
  },
  {
    "code": "HOMA",
    "name": "HOMA",
    "suggested_price_from_lab": 1941,
    "price": "$3.106"
  },
  {
    "code": "HMC",
    "name": "HOMOCISTEINA en orina",
    "suggested_price_from_lab": 10401,
    "price": "$16.642"
  },
  {
    "code": "HMS",
    "name": "HOMOCISTEINA en sangre",
    "suggested_price_from_lab": 7011,
    "price": "$11.218"
  },
  {
    "code": "AHO",
    "name": "HOMOVANILICO ACIDO",
    "suggested_price_from_lab": 25706,
    "price": "$41.130"
  },
  {
    "code": "AMH",
    "name": "HORMONA ANTI MULLERIANA",
    "suggested_price_from_lab": 50700,
    "price": "$81.120"
  },
  {
    "code": "ADH",
    "name": "HORMONA ANTIDIURETICA",
    "suggested_price_from_lab": 189526,
    "price": "$303.242"
  },
  {
    "code": "HUD",
    "name": "HUDDLESSON REACCION DE",
    "suggested_price_from_lab": 4346,
    "price": "$6.954"
  },
  {
    "code": "IGA",
    "name": "INMUNOGLOBULINA A - IGA",
    "suggested_price_from_lab": 2316,
    "price": "$3.706"
  },
  {
    "code": "IGAS",
    "name": "IGA SALIVAL",
    "suggested_price_from_lab": 3216,
    "price": "$5.146"
  },
  {
    "code": "IGE",
    "name": "INMUNOGLOBULINA E - IGE",
    "suggested_price_from_lab": 2449,
    "price": "$3.918"
  },
  {
    "code": "R CAR V",
    "name": "IGE ESPEC CARNE VACUNA",
    "suggested_price_from_lab": 6843,
    "price": "$10.949"
  },
  {
    "code": "R ABEJA",
    "name": "IGE ESPECIFICA ABEJA",
    "suggested_price_from_lab": 6843,
    "price": "$10.949"
  },
  {
    "code": "R ACARO",
    "name": "IGE ESPECIFICA ACAROS",
    "suggested_price_from_lab": 6843,
    "price": "$10.949"
  },
  {
    "code": "R A-SIRO",
    "name": "IGE ESPECIFICA ACARUS SIRO",
    "suggested_price_from_lab": 6843,
    "price": "$10.949"
  },
  {
    "code": "R AJI",
    "name": "IGE ESPECIFICA AJI COLORADO",
    "suggested_price_from_lab": 6843,
    "price": "$10.949"
  },
  {
    "code": "R ALAMO",
    "name": "IGE ESPECIFICA ALAMO",
    "suggested_price_from_lab": 6843,
    "price": "$10.949"
  },
  {
    "code": "R A LACT",
    "name": "IGE ESPECIFICA ALFA-LACTOALBUMINA",
    "suggested_price_from_lab": 6843,
    "price": "$10.949"
  },
  {
    "code": "R ALMEN",
    "name": "IGE ESPECIFICA ALMENDRAS",
    "suggested_price_from_lab": 6843,
    "price": "$10.949"
  },
  {
    "code": "R ALTER",
    "name": "IGE ESPECIFICA ALTERNARIA",
    "suggested_price_from_lab": 6843,
    "price": "$10.949"
  },
  {
    "code": "R AMARA",
    "name": "IGE ESPECIFICA AMARANTUS",
    "suggested_price_from_lab": 6843,
    "price": "$10.949"
  },
  {
    "code": "R AMBRO",
    "name": "IGE ESPECIFICA AMBROSIA",
    "suggested_price_from_lab": 6843,
    "price": "$10.949"
  },
  {
    "code": "R AMOXI",
    "name": "IGE ESPECIFICA AMOXICILINA",
    "suggested_price_from_lab": 6843,
    "price": "$10.949"
  },
  {
    "code": "R ARBOL",
    "name": "IGE ESPECIFICA ARBOL",
    "suggested_price_from_lab": 6843,
    "price": "$10.949"
  },
  {
    "code": "R ARBUST",
    "name": "IGE ESPECIFICA ARBUSTO",
    "suggested_price_from_lab": 6843,
    "price": "$10.949"
  },
  {
    "code": "R ARCE",
    "name": "IGE ESPECIFICA ARCE",
    "suggested_price_from_lab": 6843,
    "price": "$10.949"
  },
  {
    "code": "R ASP-NI",
    "name": "IGE ESPECIFICA ARPERGILLUS NIGER",
    "suggested_price_from_lab": 6843,
    "price": "$10.949"
  },
  {
    "code": "R ARTEMI",
    "name": "IGE ESPECIFICA ARTEMISA",
    "suggested_price_from_lab": 6843,
    "price": "$10.949"
  },
  {
    "code": "R ASPER",
    "name": "IGE ESPECIFICA ASPERGILLUS",
    "suggested_price_from_lab": 6843,
    "price": "$10.949"
  },
  {
    "code": "R ASP-FL",
    "name": "IGE ESPECIFICA ASPERGILLUS FLAVUS",
    "suggested_price_from_lab": 6843,
    "price": "$10.949"
  },
  {
    "code": "R ASP-FU",
    "name": "IGE ESPECIFICA ASPERGILLUS FUMIGATUS",
    "suggested_price_from_lab": 6843,
    "price": "$10.949"
  },
  {
    "code": "R ANANA",
    "name": "IGE ESPECIFICA ANANA",
    "suggested_price_from_lab": 6843,
    "price": "$10.949"
  },
  {
    "code": "R AVENA",
    "name": "IGE ESPECIFICA AVENA",
    "suggested_price_from_lab": 6843,
    "price": "$10.949"
  },
  {
    "code": "R BANANA",
    "name": "IGE ESPECIFICA BANANAS",
    "suggested_price_from_lab": 6843,
    "price": "$10.949"
  },
  {
    "code": "R B LACT",
    "name": "IGE ESPECIFICA BETA-LACTOGLOBULINA",
    "suggested_price_from_lab": 6843,
    "price": "$10.949"
  },
  {
    "code": "R CACAO",
    "name": "IGE ESPECIFICA CACAO",
    "suggested_price_from_lab": 6843,
    "price": "$10.949"
  },
  {
    "code": "R CAMAR",
    "name": "IGE ESPECIFICA CAMARON",
    "suggested_price_from_lab": 6843,
    "price": "$10.949"
  },
  {
    "code": "R CANDI",
    "name": "IGE ESPECIFICA CANDIDA ALBICANS",
    "suggested_price_from_lab": 6843,
    "price": "$10.949"
  },
  {
    "code": "R CASEIN",
    "name": "IGE ESPECIFICA CASEINA",
    "suggested_price_from_lab": 6843,
    "price": "$10.949"
  },
  {
    "code": "R H-CLAR",
    "name": "IGE ESPECIFICA CLARA DE HUEVO",
    "suggested_price_from_lab": 6843,
    "price": "$10.949"
  },
  {
    "code": "R CAB-E",
    "name": "IGE ESPECIFICA EPITELIO DE CABALLO",
    "suggested_price_from_lab": 6843,
    "price": "$10.949"
  },
  {
    "code": "R FRUTI",
    "name": "IGE ESPECIFICA FRUTILLAS",
    "suggested_price_from_lab": 6843,
    "price": "$10.949"
  },
  {
    "code": "R LACTOA",
    "name": "IGE ESPECIFICA LACTOALBUMINA",
    "suggested_price_from_lab": 6843,
    "price": "$10.949"
  },
  {
    "code": "R LECHE",
    "name": "IGE ESPECIFICA LECHE",
    "suggested_price_from_lab": 6843,
    "price": "$10.949"
  },
  {
    "code": "R NUEZ",
    "name": "IGE ESPECIFICA NUEZ",
    "suggested_price_from_lab": 6843,
    "price": "$10.949"
  },
  {
    "code": "R OVO",
    "name": "IGE ESPECIFICA OVOALBUMINA",
    "suggested_price_from_lab": 6843,
    "price": "$10.949"
  },
  {
    "code": "R SOJA",
    "name": "IGE ESPECIFICA SOJA",
    "suggested_price_from_lab": 6843,
    "price": "$10.949"
  },
  {
    "code": "R TOMA",
    "name": "IGE ESPECIFICA TOMATE",
    "suggested_price_from_lab": 6843,
    "price": "$10.949"
  },
  {
    "code": "R OTROS",
    "name": "IGE ESPECIFICOS OTROS",
    "suggested_price_from_lab": 6843,
    "price": "$10.949"
  },
  {
    "code": "R PENIN",
    "name": "IgE ESPECIFICA - PENICILINA INYECTABLE",
    "suggested_price_from_lab": 6843,
    "price": "$10.949"
  },
  {
    "code": "IGF",
    "name": "IGF-I   -  SOMATOMEDINA C",
    "suggested_price_from_lab": 10959,
    "price": "$17.534"
  },
  {
    "code": "IGG",
    "name": "INMUNOGLOBULINA G -IGG",
    "suggested_price_from_lab": 1856,
    "price": "$2.970"
  },
  {
    "code": "IGM",
    "name": "INMUNOGLOBULINA M - IGM",
    "suggested_price_from_lab": 1856,
    "price": "$2.970"
  },
  {
    "code": "INSUL",
    "name": "INSULINA SERICA TOTAL",
    "suggested_price_from_lab": 2065,
    "price": "$3.304"
  },
  {
    "code": "ION",
    "name": "IONOGRAMA PLASMATICO",
    "suggested_price_from_lab": 1172,
    "price": "$1.875"
  },
  {
    "code": "IOU",
    "name": "IONOGRAMA URINARIO",
    "suggested_price_from_lab": 1228,
    "price": "$1.965"
  },
  {
    "code": "LDH",
    "name": "LACTICO DEHIDROGENASA LDH",
    "suggested_price_from_lab": 956,
    "price": "$1.530"
  },
  {
    "code": "LAM",
    "name": "LAMOTRIGINA",
    "suggested_price_from_lab": 39267,
    "price": "$62.827"
  },
  {
    "code": "LARC",
    "name": "LATEX ARTRITIS REUMATOIDEA CUANTITATIVO",
    "suggested_price_from_lab": 1786,
    "price": "$2.858"
  },
  {
    "code": "LMF",
    "name": "LEUCOCITOS EN MATERIA FECAL",
    "suggested_price_from_lab": 11308,
    "price": "$18.093"
  },
  {
    "code": "LH",
    "name": "LH HORMONA LUTEOTROFICA",
    "suggested_price_from_lab": 2044,
    "price": "$3.270"
  },
  {
    "code": "LIP",
    "name": "LIPEMIA O LIPIDOS TOTALES EN SAN",
    "suggested_price_from_lab": 1842,
    "price": "$2.947"
  },
  {
    "code": "LIG",
    "name": "LIPIDOGRAMA ELECTROFORETICO",
    "suggested_price_from_lab": 1960,
    "price": "$3.136"
  },
  {
    "code": "LPA",
    "name": "LIPOPROTEINA A",
    "suggested_price_from_lab": 9954,
    "price": "$15.926"
  },
  {
    "code": "LIT",
    "name": "LITIO PLASMATICO",
    "suggested_price_from_lab": 3934,
    "price": "$6.294"
  },
  {
    "code": "ILU",
    "name": "LUPICO ANTICOAGULANTE O INHIBIDOR",
    "suggested_price_from_lab": 30156,
    "price": "$48.250"
  },
  {
    "code": "MGU",
    "name": "MAGNESIO en orina",
    "suggested_price_from_lab": 1295,
    "price": "$2.072"
  },
  {
    "code": "MGS",
    "name": "MAGNESIO en sangre",
    "suggested_price_from_lab": 1295,
    "price": "$2.072"
  },
  {
    "code": "AMANDE",
    "name": "MANDELICO ACIDO",
    "suggested_price_from_lab": 30575,
    "price": "$48.920"
  },
  {
    "code": "PPD",
    "name": "MANTOUX INTRADERMORREACCION",
    "suggested_price_from_lab": 5391,
    "price": "$8.626"
  },
  {
    "code": "MET",
    "name": "METANEFRINA en orina",
    "suggested_price_from_lab": 31468,
    "price": "$50.349"
  },
  {
    "code": "AC METIL",
    "name": "METIL HIPURICO ACIDO  en ORINA",
    "suggested_price_from_lab": 17628,
    "price": "$28.205"
  },
  {
    "code": "MIC1",
    "name": "MICOLOGICO",
    "suggested_price_from_lab": 15591,
    "price": "$24.946"
  },
  {
    "code": "ALB-U2",
    "name": "MICROALBUMINURIA (Orina 2 hs)",
    "suggested_price_from_lab": 3146,
    "price": "$5.034"
  },
  {
    "code": "ALB-U",
    "name": "MICROALBUMINURIA - ALBUMINA EN ORINA",
    "suggested_price_from_lab": 4054,
    "price": "$6.486"
  },
  {
    "code": "ALB-UE",
    "name": "MICROALBUMINURIA EN ORINA ESPONTANEA",
    "suggested_price_from_lab": 3146,
    "price": "$5.034"
  },
  {
    "code": "AMAM2",
    "name": "MITOCONDRIAL TIPO 2",
    "suggested_price_from_lab": 23732,
    "price": "$37.971"
  },
  {
    "code": "MONO",
    "name": "MONO TEST",
    "suggested_price_from_lab": 1751,
    "price": "$2.802"
  },
  {
    "code": "MYC",
    "name": "MYCOPLASMA CULTIVO",
    "suggested_price_from_lab": 72163,
    "price": "$115.461"
  },
  {
    "code": "ORI",
    "name": "ORINA COMPLETA",
    "suggested_price_from_lab": 2790,
    "price": "$4.464"
  },
  {
    "code": "PMF",
    "name": "PARAS. MAT FECAL",
    "suggested_price_from_lab": 2790,
    "price": "$4.464"
  },
  {
    "code": "PTH",
    "name": "PARATHORMONA",
    "suggested_price_from_lab": 2637,
    "price": "$4.219"
  },
  {
    "code": "PARO G",
    "name": "PAROTIDITIS ANTIC.ANTI IgG",
    "suggested_price_from_lab": 32458,
    "price": "$51.933"
  },
  {
    "code": "PARO M",
    "name": "PAROTIDITIS ANTIC.ANTI IgM",
    "suggested_price_from_lab": 31817,
    "price": "$50.907"
  },
  {
    "code": "BNP",
    "name": "PRO BNP",
    "suggested_price_from_lab": 56344,
    "price": "$90.150"
  },
  {
    "code": "PRO CAL",
    "name": "PROCALCITONINA",
    "suggested_price_from_lab": 34335,
    "price": "$54.936"
  },
  {
    "code": "PG",
    "name": "PROGESTERONA PLASMATICA",
    "suggested_price_from_lab": 2090,
    "price": "$3.344"
  },
  {
    "code": "PL",
    "name": "PROLACTINA",
    "suggested_price_from_lab": 2009,
    "price": "$3.214"
  },
  {
    "code": "PCR",
    "name": "PCR",
    "suggested_price_from_lab": 4924,
    "price": "$7.878"
  },
  {
    "code": "PPDMAN",
    "name": "PPD MANTOUX",
    "suggested_price_from_lab": 5391,
    "price": "$8.626"
  },
  {
    "code": "PROT C",
    "name": "PROTEINA C FUNCIONAL",
    "suggested_price_from_lab": 26438,
    "price": "$42.301"
  },
  {
    "code": "PCR",
    "name": "PROTEINA C REACTIVA",
    "suggested_price_from_lab": 4925,
    "price": "$7.880"
  },
  {
    "code": "PROS L",
    "name": "PROTEINA S LIBRE",
    "suggested_price_from_lab": 28817,
    "price": "$46.107"
  },
  {
    "code": "PRO",
    "name": "PROTEINAS TOTALES",
    "suggested_price_from_lab": 12459,
    "price": "$19.934"
  },
  {
    "code": "PRU",
    "name": "PROTEINAS URINARIAS 12/24 hs",
    "suggested_price_from_lab": 2589,
    "price": "$4.142"
  },
  {
    "code": "PTG",
    "name": "PROTEINOGRAMA",
    "suggested_price_from_lab": 12459,
    "price": "$19.934"
  },
  {
    "code": 20210,
    "name": "PROTOMBINA 20210",
    "suggested_price_from_lab": 79015,
    "price": "$126.424"
  },
  {
    "code": "PRR",
    "name": "PRUEBA DE ROSSE RAGAN",
    "suggested_price_from_lab": 11099,
    "price": "$17.758"
  },
  {
    "code": "RPCA",
    "name": "RESIST. A LA PROTEINA C ACTIVA",
    "suggested_price_from_lab": 27122,
    "price": "$43.395"
  },
  {
    "code": "RET",
    "name": "RETICULOCITOS",
    "suggested_price_from_lab": 1278,
    "price": "$2.045"
  },
  {
    "code": "RUG",
    "name": "RUBEOLA ANTIC.ANTI IgG ELISA",
    "suggested_price_from_lab": 5148,
    "price": "$8.237"
  },
  {
    "code": "RUM",
    "name": "RUBEOLA ANTIC.ANTI IgM ELISA",
    "suggested_price_from_lab": 4785,
    "price": "$7.656"
  },
  {
    "code": "SOM",
    "name": "SANGRE OCULTA - MATERIA FECAL",
    "suggested_price_from_lab": 4465,
    "price": "$7.144"
  },
  {
    "code": "SAT",
    "name": "SATURACION DE TRANSFERRINA",
    "suggested_price_from_lab": 2609,
    "price": "$4.174"
  },
  {
    "code": "SEL",
    "name": "SELENIO",
    "suggested_price_from_lab": 47798,
    "price": "$76.477"
  },
  {
    "code": "SER",
    "name": "SEROTONINA",
    "suggested_price_from_lab": 34984,
    "price": "$55.974"
  },
  {
    "code": "SER-O",
    "name": "SEROTONINA EN ORINA DE 24HS",
    "suggested_price_from_lab": 43125,
    "price": "$69.000"
  },
  {
    "code": "HGH",
    "name": "SOMATOTROFINA",
    "suggested_price_from_lab": 4269,
    "price": "$6.830"
  },
  {
    "code": "SUBCUAN",
    "name": "SUB UNIDAD BETA CUANTITATIVA",
    "suggested_price_from_lab": 5455,
    "price": "$8.728"
  },
  {
    "code": "SUBCUAL",
    "name": "SUB UNIDAD BETA CUALITATIVA",
    "suggested_price_from_lab": 2728,
    "price": "$4.365"
  },
  {
    "code": "DHEAS",
    "name": "SULFATO DEHIDROEPIANDROSTERONA",
    "suggested_price_from_lab": 3293,
    "price": "$5.269"
  },
  {
    "code": "T3",
    "name": "T3 - TRIIODOTIRONINA",
    "suggested_price_from_lab": 2682,
    "price": "$4.291"
  },
  {
    "code": "T3L",
    "name": "T3 LIBRE",
    "suggested_price_from_lab": 4082,
    "price": "$6.531"
  },
  {
    "code": "T4",
    "name": "T4 - TIROXINA TOTAL",
    "suggested_price_from_lab": 1317,
    "price": "$2.107"
  },
  {
    "code": "T4L",
    "name": "T4 LIBRE",
    "suggested_price_from_lab": 2682,
    "price": "$4.291"
  },
  {
    "code": "GHM",
    "name": "TEST DE GRAHAM",
    "suggested_price_from_lab": 2341,
    "price": "$3.746"
  },
  {
    "code": "TEB",
    "name": "TESTOSTERONA BIODISPONIBLE",
    "suggested_price_from_lab": 5929,
    "price": "$9.486"
  },
  {
    "code": "TEL",
    "name": "TESTOSTERONA LIBRE en suero",
    "suggested_price_from_lab": 4109,
    "price": "$6.574"
  },
  {
    "code": "TES",
    "name": "TESTOSTERONA PLASMATICA",
    "suggested_price_from_lab": 1844,
    "price": "$2.950"
  },
  {
    "code": "TG",
    "name": "TIROGLOBULINA",
    "suggested_price_from_lab": 3153,
    "price": "$5.045"
  },
  {
    "code": "TXG",
    "name": "TOXOPLASMOSIS ANTIC. IgG",
    "suggested_price_from_lab": 4611,
    "price": "$7.378"
  },
  {
    "code": "TX-AVI",
    "name": "TOXOPLASMOSIS ANTIC.ANTI IgG AVIDEZ",
    "suggested_price_from_lab": 15849,
    "price": "$25.358"
  },
  {
    "code": "TXM",
    "name": "TOXOPLASMOSIS IgM-IFI REMINGTON T.DE",
    "suggested_price_from_lab": 5323,
    "price": "$8.517"
  },
  {
    "code": "TRABS",
    "name": "TRABS",
    "suggested_price_from_lab": 20768,
    "price": "$33.229"
  },
  {
    "code": "TGO",
    "name": "TRANSAMINASA GLUTAMICO OXALACETICA (TGO/GOT)",
    "suggested_price_from_lab": 893,
    "price": "$1.429"
  },
  {
    "code": "TGP",
    "name": "TRANSAMINASA GLUTAMINASA PIRIVICA (TGP- GPT)",
    "suggested_price_from_lab": 893,
    "price": "$1.429"
  },
  {
    "code": "TRA",
    "name": "TRANSFERRINA",
    "suggested_price_from_lab": 2058,
    "price": "$3.293"
  },
  {
    "code": "TGL",
    "name": "TRIGLICERIDOS",
    "suggested_price_from_lab": 1939,
    "price": "$3.102"
  },
  {
    "code": "TROPO",
    "name": "TROPONINA T (Tn-T)",
    "suggested_price_from_lab": 14077,
    "price": "$22.523"
  },
  {
    "code": "TSH",
    "name": "TSH - TIROTROFINA PLASMATICA",
    "suggested_price_from_lab": 1116,
    "price": "$1.786"
  },
  {
    "code": "CDU",
    "name": "UREA, CLEARENCE DE",
    "suggested_price_from_lab": 1306,
    "price": "$2.090"
  },
  {
    "code": "UUREAL",
    "name": "UREAPLASMA UREALITICUM CULT.",
    "suggested_price_from_lab": 65528,
    "price": "$104.845"
  },
  {
    "code": "URE",
    "name": "UREMIA",
    "suggested_price_from_lab": 1055,
    "price": "$1.688"
  },
  {
    "code": "AUR",
    "name": "URICO ACIDO",
    "suggested_price_from_lab": 1306,
    "price": "$2.090"
  },
  {
    "code": "AUUE",
    "name": "URICO ACIDO  EN ORINA OCASIONAL",
    "suggested_price_from_lab": 1306,
    "price": "$2.090"
  },
  {
    "code": "AUU2",
    "name": "URICO ACIDO  en orina de 2 hs.",
    "suggested_price_from_lab": 1306,
    "price": "$2.090"
  },
  {
    "code": "AUU",
    "name": "URICO ACIDO orina",
    "suggested_price_from_lab": 1306,
    "price": "$2.090"
  },
  {
    "code": "UROANT",
    "name": "UROCULTIVO + ANTIBIOGRAMA",
    "suggested_price_from_lab": 12724,
    "price": "$20.358"
  },
  {
    "code": "VDR",
    "name": "V.D.R.L. CUALITATIVA",
    "suggested_price_from_lab": 1646,
    "price": "$2.634"
  },
  {
    "code": "VDC",
    "name": "V.D.R.L. CUANTITATIVA",
    "suggested_price_from_lab": 2469,
    "price": "$3.950"
  },
  {
    "code": "FVTIP+",
    "name": "VAGINAL FLUJO C/TIP + Y ANTIBIOG.",
    "suggested_price_from_lab": 17903,
    "price": "$28.645"
  },
  {
    "code": "AVM",
    "name": "VAINILLIN MANDELICO ACIDO",
    "suggested_price_from_lab": 30575,
    "price": "$48.920"
  },
  {
    "code": "VAL",
    "name": "VALPROICO ACIDO",
    "suggested_price_from_lab": 4953,
    "price": "$7.925"
  },
  {
    "code": "VARI G",
    "name": "VARICELA ANTIC.ANTI IgG IFI",
    "suggested_price_from_lab": 17851,
    "price": "$28.562"
  },
  {
    "code": "VARI M",
    "name": "VARICELA ANTIC.ANTI IgM IFI",
    "suggested_price_from_lab": 14684,
    "price": "$23.494"
  },
  {
    "code": "VB1",
    "name": "VITAMINA B1 - TIAMINA",
    "suggested_price_from_lab": 42329,
    "price": "$67.726"
  },
  {
    "code": "B12",
    "name": "VITAMINA B12",
    "suggested_price_from_lab": 3041,
    "price": "$4.866"
  },
  {
    "code": "VB6",
    "name": "VITAMINA B6 - PIRIDOXINA",
    "suggested_price_from_lab": 42329,
    "price": "$67.726"
  },
  {
    "code": "VIC",
    "name": "VITAMINA C - ACIDO ASCORBICO",
    "suggested_price_from_lab": 42329,
    "price": "$67.726"
  },
  {
    "code": "V25",
    "name": "VITAMINA D3, 25 HIDROXI",
    "suggested_price_from_lab": 11545,
    "price": "$18.472"
  },
  {
    "code": "ZIN",
    "name": "ZINC SERICO",
    "suggested_price_from_lab": 16568,
    "price": "$26.509"
  }
]